pyelitecloud/__init__.py
pyelitecloud/api_async.py
pyelitecloud/api_sync.py
pyelitecloud/const.py
pyelitecloud/data.py
pyelitecloud/diagnostics.py
pyelitecloud/tasks.py
pyelitecloud/ws_async.py
pyelitecloud/ws_sync.py
pyelitecloud-0.1.3.dist-info/licenses/LICENSE
pyelitecloud-0.1.3.dist-info/METADATA
pyelitecloud-0.1.3.dist-info/WHEEL
pyelitecloud-0.1.3.dist-info/top_level.txt
pyelitecloud-0.1.3.dist-info/RECORD
