Metadata-Version: 2.4
Name: pyelitecloud
Version: 0.1.3
Summary: Python library to communicate with Arrowhead Alarm devices via EliteCloud
Author-email: Anko Hanse <anko_hanse@hotmail.com>
Project-URL: Homepage, https://github.com/ankohanse/pyelitecloud
Project-URL: Issues, https://github.com/ankohanse/pyelitecloud/issues
Classifier: Programming Language :: Python :: 3
Classifier: License :: OSI Approved :: GNU General Public License v3 or later (GPLv3+)
Classifier: Operating System :: OS Independent
Requires-Python: >=3.8
License-File: LICENSE
Requires-Dist: PyJWT
Requires-Dist: httpx
Requires-Dist: httpx-ws
Provides-Extra: tests
Requires-Dist: pytest; extra == "tests"
Requires-Dist: pytest-asyncio; extra == "tests"
Dynamic: license-file
